CordForge/__init__.py
CordForge/__main__.py
CordForge/card.py
CordForge/colors.py
CordForge/cord.py
CordForge/data.py
CordForge/font.py
CordForge/launcher.py
CordForge/object.py
CordForge/user.py
CordForge/utilities.py
CordForge/vector2.py
CordForge/components/__init__.py
CordForge/components/board.py
CordForge/components/board_item.py
CordForge/components/component.py
CordForge/components/line.py
CordForge/components/panel.py
CordForge/components/sprite.py
CordForge/components/text.py
CordForge/tests/__init__.py
CordForge/tests/test_card.py
CordForge/tests/test_launcher.py
CordForge/tests/test_user.py
cordforge-0.3.19.dist-info/licenses/LICENSE
cordforge-0.3.19.dist-info/METADATA
cordforge-0.3.19.dist-info/WHEEL
cordforge-0.3.19.dist-info/entry_points.txt
cordforge-0.3.19.dist-info/top_level.txt
cordforge-0.3.19.dist-info/RECORD
