Metadata-Version: 2.4
Name: CordForge
Version: 0.3.19
Summary: Discord Bot Library - UI & Image Manipulation for Making Games
Home-page: https://github.com/Robert-DeForrest-Reynolds/CordForge
Author: Robert Lawrence DeForrest Reynolds
License-Expression: MIT
Project-URL: Homepage, https://github.com/Robert-DeForrest-Reynolds/CordForge
Project-URL: Repository, https://github.com/Robert-DeForrest-Reynolds/CordForge
Keywords: discord,discord-bot,discord-bot-library,discord-games
Requires-Python: >=3.13
License-File: LICENSE
Requires-Dist: discord.py>=2.6.0
Requires-Dist: Pillow>=10.0.0
Dynamic: license-file
